cipher_wl2722/__init__.py
cipher_wl2722/cipher_wl2722.py
cipher_wl2722-0.1.0.dist-info/LICENSE
cipher_wl2722-0.1.0.dist-info/WHEEL
cipher_wl2722-0.1.0.dist-info/METADATA
cipher_wl2722-0.1.0.dist-info/RECORD
